hash_rename/__init__.py
hash_rename/__main__.py
hash_rename/cli.py
hash_rename/core.py
hash_rename-0.3.1.dist-info/METADATA
hash_rename-0.3.1.dist-info/WHEEL
hash_rename-0.3.1.dist-info/entry_points.txt
hash_rename-0.3.1.dist-info/licenses/LICENSE
hash_rename-0.3.1.dist-info/RECORD
