Metadata-Version: 2.3
Name: hash_rename
Version: 0.3.1
Summary: A tool to rename files in a folder to be prefixed with a hash of the file's contents
Project-URL: homepage, https://github.com/DeflateAwning/hash_rename
Project-URL: repository, https://github.com/DeflateAwning/hash_rename
Project-URL: issues, https://github.com/DeflateAwning/hash_rename/issues
Project-URL: license, https://github.com/DeflateAwning/hash_rename/blob/main/LICENSE
Project-URL: pypi, https://pypi.org/project/hash-rename
Author: DeflateAwning
License-Expression: Unlicense
License-File: LICENSE
Classifier: License :: OSI Approved :: The Unlicense (Unlicense)
Classifier: Operating System :: OS Independent
Classifier: Programming Language :: Python :: 3
